algebreb/__init__.py
algebreb/ejercicios/__init__.py
algebreb/ejercicios/ecuaciones_multivariables.py
algebreb/ejercicios/ecuaciones_univariables.py
algebreb/ejercicios/ejercicios_factories.py
algebreb/ejercicios/factorizacion.py
algebreb/ejercicios/operaciones_fracciones.py
algebreb/ejercicios/operaciones_polinomio.py
algebreb/ejercicios/productos_notables.py
algebreb/ejercicios/tipos_ejercicios.py
algebreb/ejercicios/ejemplos/__init__.py
algebreb/expresiones/__init__.py
algebreb/expresiones/expresiones_factories.py
algebreb/expresiones/fracciones_algebraicas.py
algebreb/expresiones/polinomios.py
algebreb/expresiones/ejemplos/__init__.py
algebreb/expresiones/ejemplos/ejemplo_polinomio_coeficientes_aleatorios.py
algebreb/expresiones/ejemplos/ejemplo_polinomio_raices_aleatorias.py
algebreb/listas/__init__.py
algebreb/listas/lista.py
algebreb/listas/listas_ecuaciones_multivariables.py
algebreb/listas/listas_ecuaciones_univariables.py
algebreb/listas/listas_factorizacion.py
algebreb/listas/listas_fracciones_algebraicas.py
algebreb/listas/listas_polinomios.py
algebreb/listas/listas_productos_notables.py
algebreb/pasos/__init__.py
algebreb/pasos/factorizacion.py
algebreb/pasos/fracciones_algebraicas.py
algebreb/pasos/polinomios.py
algebreb/pasos/productos_notables.py
algebreb/util/__init__.py
algebreb/util/numeros.py
algebreb/util/numeros_proxy.py
algebreb/util/terminos.py
algebreb/util/util.py
algebreb/util/ejemplos/__init__.py
algebreb/util/ejemplos/ejemplos_numeros/__init__.py
algebreb/util/ejemplos/ejemplos_numeros/ejemplos_decimal_aleatorio.py
algebreb/util/ejemplos/ejemplos_numeros/ejemplos_decimales_aleatorios.py
algebreb/util/ejemplos/ejemplos_numeros/ejemplos_entero_aleatorio.py
algebreb/util/ejemplos/ejemplos_numeros/ejemplos_enteros_aleatorios.py
algebreb/util/ejemplos/ejemplos_numeros/ejemplos_fraccion_aleatoria.py
algebreb/util/ejemplos/ejemplos_numeros/ejemplos_fracciones_aleatorias.py
algebreb/util/ejemplos/ejemplos_numeros/ejemplos_nulos.py
algebreb-4.0.dist-info/LICENSE
algebreb-4.0.dist-info/METADATA
algebreb-4.0.dist-info/WHEEL
algebreb-4.0.dist-info/top_level.txt
algebreb-4.0.dist-info/RECORD
