Metadata-Version: 2.1
Name: algebreb
Version: 4.0
Summary: Biblioteca para generar expresiones y ejercicios de algebra
Home-page: UNKNOWN
Author: ivan0123456789
Author-email: <elite-a64@outlook.com>
License: UNKNOWN
Keywords: python,algebra
Platform: UNKNOWN
Classifier: Development Status :: 1 - Planning
Classifier: Intended Audience :: Developers
Classifier: Programming Language :: Python :: 3
Classifier: Operating System :: Unix
Classifier: Operating System :: MacOS :: MacOS X
Classifier: Operating System :: Microsoft :: Windows
Requires-Dist: sympy
